passpwnedcheck/__init__.py
passpwnedcheck/constants.py
passpwnedcheck/pass_checker.py
passpwnedcheck/pass_checker_async.py
passpwnedcheck/session_manager.py
passpwnedcheck/utils.py
passpwnedcheck-2.0.0.dist-info/LICENSE.txt
passpwnedcheck-2.0.0.dist-info/METADATA
passpwnedcheck-2.0.0.dist-info/WHEEL
passpwnedcheck-2.0.0.dist-info/top_level.txt
passpwnedcheck-2.0.0.dist-info/RECORD
