Metadata-Version: 2.1
Name: passpwnedcheck
Version: 2.0.0
Summary: Test for pwned password
Home-page: https://github.com/duongntbk/passpwnedcheck
Author: Nguyen Thai Duong
Author-email: duongnt.bk@gmail.com
License: UNKNOWN
Platform: UNKNOWN
Classifier: Programming Language :: Python :: 3
Classifier: License :: OSI Approved :: MIT License
Classifier: Operating System :: OS Independent
License-File: LICENSE.txt
Requires-Dist: requests (>=2.19.1)
Requires-Dist: aiohttp (>=3.7.4)
